reoxide/__init__.py
reoxide/config.py
reoxide/plugin.py
reoxide/reoxide.py
reoxide/data/default.yaml
reoxide/data/bin/decompile
reoxide/data/bin/libcore.so
reoxide/data/bin/libprintmir.so
reoxide/data/bin/libprintrust.so
reoxide/data/bin/libreoxide.so
reoxide/data/include/ghidra/LICENSE
reoxide/data/include/ghidra/NOTICE
reoxide/data/include/ghidra/action.hh
reoxide/data/include/ghidra/address.hh
reoxide/data/include/ghidra/architecture.hh
reoxide/data/include/ghidra/block.hh
reoxide/data/include/ghidra/blockaction.hh
reoxide/data/include/ghidra/callgraph.hh
reoxide/data/include/ghidra/capability.hh
reoxide/data/include/ghidra/cast.hh
reoxide/data/include/ghidra/comment.hh
reoxide/data/include/ghidra/compression.hh
reoxide/data/include/ghidra/condexe.hh
reoxide/data/include/ghidra/constseq.hh
reoxide/data/include/ghidra/context.hh
reoxide/data/include/ghidra/coreaction.hh
reoxide/data/include/ghidra/cover.hh
reoxide/data/include/ghidra/cpool.hh
reoxide/data/include/ghidra/crc32.hh
reoxide/data/include/ghidra/database.hh
reoxide/data/include/ghidra/double.hh
reoxide/data/include/ghidra/dynamic.hh
reoxide/data/include/ghidra/emulate.hh
reoxide/data/include/ghidra/emulateutil.hh
reoxide/data/include/ghidra/error.hh
reoxide/data/include/ghidra/expression.hh
reoxide/data/include/ghidra/filemanage.hh
reoxide/data/include/ghidra/float.hh
reoxide/data/include/ghidra/flow.hh
reoxide/data/include/ghidra/fspec.hh
reoxide/data/include/ghidra/funcdata.hh
reoxide/data/include/ghidra/globalcontext.hh
reoxide/data/include/ghidra/grammar.hh
reoxide/data/include/ghidra/graph.hh
reoxide/data/include/ghidra/heritage.hh
reoxide/data/include/ghidra/ifacedecomp.hh
reoxide/data/include/ghidra/ifaceterm.hh
reoxide/data/include/ghidra/inject_sleigh.hh
reoxide/data/include/ghidra/interface.hh
reoxide/data/include/ghidra/jumptable.hh
reoxide/data/include/ghidra/libdecomp.hh
reoxide/data/include/ghidra/loadimage.hh
reoxide-0.8.0.dist-info/LICENSE
reoxide-0.8.0.dist-info/METADATA
reoxide-0.8.0.dist-info/WHEEL
reoxide-0.8.0.dist-info/entry_points.txt
reoxide-0.8.0.dist-info/RECORD
