Metadata-Version: 2.1
Name: reoxide
Version: 0.8.0
Summary: A Plugin System for the Ghidra Decompiler.
Author-Email: Michael Pucher <contact@cluo.sh>
License:                                  Apache License
Classifier: Development Status :: 3 - Alpha
Classifier: Intended Audience :: Developers
Classifier: Environment :: Console
Classifier: Topic :: Security
Classifier: Topic :: Software Development :: Disassemblers
Classifier: Operating System :: POSIX :: Linux
Classifier: Programming Language :: C++
Classifier: Programming Language :: Python
Classifier: Programming Language :: Rust
Classifier: Programming Language :: Python :: 3.11
Project-URL: Homepage, https://reoxide.eu
Project-URL: Documentation, https://reoxide.eu/guide/getting-started
Project-URL: Repository, https://codeberg.org/ReOxide/reoxide.git
Project-URL: Issues, https://codeberg.org/ReOxide/reoxide/issues
Requires-Python: >=3.10
Requires-Dist: platformdirs>=4.3.6
Requires-Dist: PyYAML>=6.0.2
Requires-Dist: pyzmq>=26.2.0
Requires-Dist: tomli>=1.1.0; python_version < "3.11"
Provides-Extra: gui
Requires-Dist: PySide6>=6.9.2; extra == "gui"
